Lupv
