Metadata-Version: 2.1
Name: Lupv
Version: 1.6.37
Summary: Lup viewer
Home-page: https://gitlab.com/azzamsa/lupv
Author: azzamsa
Author-email: azzam@azzamsa.com
License: GPLv3
Platform: UNKNOWN
Classifier: License :: OSI Approved :: MIT License
Classifier: Programming Language :: Python :: 3
Classifier: Programming Language :: Python :: 3.6
Classifier: Programming Language :: Python :: Implementation :: CPython
